flask_inputs/__init__.py
flask_inputs/inputs.py
flask_inputs/validators.py
Flask_Inputs-1.0.0.dist-info/LICENSE.md
Flask_Inputs-1.0.0.dist-info/METADATA
Flask_Inputs-1.0.0.dist-info/WHEEL
Flask_Inputs-1.0.0.dist-info/top_level.txt
Flask_Inputs-1.0.0.dist-info/RECORD
