Metadata-Version: 2.1
Name: Flask-Inputs
Version: 1.0.0
Summary: Flask request data validation
Home-page: http://pythonhosted.org/Flask-Inputs
Author: David Parker
Author-email: durera@gmail.com
License: MIT
Keywords: flask validation wtforms
Requires-Python: >=3.9
License-File: LICENSE.md
Requires-Dist: flask >=3
Requires-Dist: wtforms >=3
Requires-Dist: future >=1
Provides-Extra: dev
Requires-Dist: build ; extra == 'dev'
Requires-Dist: pytest ; extra == 'dev'
Requires-Dist: email-validator ; extra == 'dev'
Requires-Dist: jsonschema ; extra == 'dev'
